README.md
setup.cfg
setup.py
seearh_distributions/Binomialdistribution.py
seearh_distributions/Gaussiandistribution.py
seearh_distributions/Generaldistribution.py
seearh_distributions/__init__.py
seearh_distributions.egg-info/PKG-INFO
seearh_distributions.egg-info/SOURCES.txt
seearh_distributions.egg-info/dependency_links.txt
seearh_distributions.egg-info/not-zip-safe
seearh_distributions.egg-info/top_level.txt