Metadata-Version: 1.0
Name: seearh-distributions
Version: 0.1
Summary: Gaussian distributions
Home-page: UNKNOWN
Author: seearh
Author-email: congrun@hotmail.com
License: UNKNOWN
Platform: UNKNOWN
